ai_header_generator/__init__.py
ai_header_generator/cli.py
ai_header_generator/header_generator.py
ai_header_generator/misc.py
ai_header_generator-0.1.dist-info/METADATA
ai_header_generator-0.1.dist-info/PKG-INFO_req.markup
ai_header_generator-0.1.dist-info/WHEEL
ai_header_generator-0.1.dist-info/entry_points.txt
ai_header_generator-0.1.dist-info/top_level.txt
ai_header_generator-0.1.dist-info/RECORD
