Metadata-Version: 2.1
Name: ai-header-generator
Version: 0.1
Summary: UNKNOWN
Home-page: UNKNOWN
Author: UNKNOWN
Author-email: UNKNOWN
License: UNKNOWN
Platform: UNKNOWN
Requires-Dist: openai
Requires-Dist: argparse
Requires-Dist: configparser
Requires-Dist: jsonpickle
